ytsubtitles/__init__.py
ytsubtitles/ytsubtitles.py
ytsubtitles-0.0.4.dist-info/LICENSE
ytsubtitles-0.0.4.dist-info/METADATA
ytsubtitles-0.0.4.dist-info/WHEEL
ytsubtitles-0.0.4.dist-info/entry_points.txt
ytsubtitles-0.0.4.dist-info/top_level.txt
ytsubtitles-0.0.4.dist-info/RECORD
