Metadata-Version: 2.1
Name: ytsubtitles
Version: 0.0.4
Summary: ytsubtitles makes you download subs from youtube.
Home-page: https://github.com/vvigilante/decoripy.git
Author: Vincenzo Vigilante, Gioele Crispo
Author-email: info@vvigilante.com
License: MIT
Platform: UNKNOWN
Classifier: Development Status :: 5 - Production/Stable
Classifier: Intended Audience :: Developers
Classifier: License :: OSI Approved :: MIT License
Classifier: Programming Language :: Python
Classifier: Programming Language :: Python :: 3
Classifier: Programming Language :: Python :: 3.4
Classifier: Programming Language :: Python :: 3.5
Classifier: Programming Language :: Python :: 3.6
Classifier: Programming Language :: Python :: 3.7
Classifier: Programming Language :: Python :: Implementation :: PyPy
Classifier: Topic :: Software Development :: Libraries :: Python Modules
Requires-Python: >=3.4
